wskr/tty/transport.py
wskr/tty/registry.py
wskr/tty/__init__.py
wskr/tty/kitty_remote.py
wskr/tty/kitty.py
wskr/tty/base.py
wskr/plot.py
wskr/__init__.py
wskr/ttyools.py
wskr/mpl/sixel.py
wskr/mpl/__init__.py
wskr/mpl/iterm2.py
wskr/mpl/utils.py
wskr/mpl/kitty.py
wskr/mpl/base.py
wskr/rich/__init__.py
wskr/rich/img.py
wskr/rich/rcd.txt
wskr/rich/plt.py
wskr-0.0.3.dist-info/WHEEL
wskr-0.0.3.dist-info/entry_points.txt
wskr-0.0.3.dist-info/METADATA
wskr-0.0.3.dist-info/RECORD
