Metadata-Version: 2.3
Name: wskr
Version: 0.0.3
Summary: 
Author: Joseph Courtney
Author-email: Joseph Courtney <joseph.m.courtney@gmail.com>
License: GPL-3.0-only
Classifier: Development Status :: 3 - Alpha
Classifier: License :: OSI Approved :: GNU General Public License (GPL)
Classifier: Programming Language :: Python :: 3
Classifier: Operating System :: OS Independent
Requires-Dist: matplotlib>=3.10.1
Requires-Dist: numpy>=2.2.5
Requires-Dist: pytest-timeout>=2.4.0
Requires-Dist: rich>=14.0.0
Requires-Dist: scipy>=1.15.2
Requires-Python: >=3.13
Project-URL: Bug Tracker, https://github.com/josephcourtney/wskr/issues
Project-URL: Homepage, https://github.com/josephcourtney/wskr
